airkoreapy.py
airkoreapy-0.0.1.dist-info/licenses/LICENSE
airkoreapy-0.0.1.dist-info/METADATA
airkoreapy-0.0.1.dist-info/WHEEL
airkoreapy-0.0.1.dist-info/top_level.txt
airkoreapy-0.0.1.dist-info/RECORD
